dataflow_cookiecutter/__init__.py
dataflow_cookiecutter/cli/__init__.py
dataflow_cookiecutter/cli/config.py
dataflow_cookiecutter/cli/ls.py
dataflow_cookiecutter/cli/main.py
dataflow_cookiecutter/cli/new.py
dataflow_cookiecutter/cli/utils.py
dataflow_cookiecutter-1.0.0a3.dist-info/METADATA
dataflow_cookiecutter-1.0.0a3.dist-info/WHEEL
dataflow_cookiecutter-1.0.0a3.dist-info/dependency_links.txt
dataflow_cookiecutter-1.0.0a3.dist-info/entry_points.txt
dataflow_cookiecutter-1.0.0a3.dist-info/top_level.txt
dataflow_cookiecutter-1.0.0a3.dist-info/RECORD
