Metadata-Version: 2.1
Name: dataflow-cookiecutter
Version: 1.0.0a3
Summary: Command-line utility for creating Dataflow projects
Home-page: UNKNOWN
Author: Lester James V. Miranda
Author-email: ljvmiranda@gmail.com
License: UNKNOWN
Platform: UNKNOWN
Requires-Dist: cookiecutter
Requires-Dist: tabulate
Requires-Dist: loguru
Requires-Dist: click
